{"errors":[],"warnings":[],"namedChunkGroups":{"app":{"chunks":[10,9,2],"assets":["webpack-runtime-87c19cf21ab0e2cb5760.js","webpack-runtime-87c19cf21ab0e2cb5760.js.map","framework-b1ec57a693c63eec2e66.js","framework-b1ec57a693c63eec2e66.js.map","app-275029329b0bbb5dc6be.js","app-275029329b0bbb5dc6be.js.map"],"children":{},"childAssets":{}},"component---src-templates-blog-post-js":{"chunks":[1,0,6],"assets":["styles.e2d3033dced30e7eb194.css","styles-48fa8a050a65bb8447bd.js","styles-48fa8a050a65bb8447bd.js.map","commons-a6711baf4464e33e2ec1.js","commons-a6711baf4464e33e2ec1.js.map","component---src-templates-blog-post-js-bba17b4ded4e057a90b4.js","component---src-templates-blog-post-js-bba17b4ded4e057a90b4.js.map"],"children":{},"childAssets":{}},"component---src-pages-index-js":{"chunks":[1,0,5],"assets":["styles.e2d3033dced30e7eb194.css","styles-48fa8a050a65bb8447bd.js","styles-48fa8a050a65bb8447bd.js.map","commons-a6711baf4464e33e2ec1.js","commons-a6711baf4464e33e2ec1.js.map","component---src-pages-index-js-c7540f7aa795a623fa46.js","component---src-pages-index-js-c7540f7aa795a623fa46.js.map"],"children":{},"childAssets":{}},"component---src-templates-tags-js":{"chunks":[1,0,8],"assets":["styles.e2d3033dced30e7eb194.css","styles-48fa8a050a65bb8447bd.js","styles-48fa8a050a65bb8447bd.js.map","commons-a6711baf4464e33e2ec1.js","commons-a6711baf4464e33e2ec1.js.map","component---src-templates-tags-js-50bd6bd73abdce465f3d.js","component---src-templates-tags-js-50bd6bd73abdce465f3d.js.map"],"children":{},"childAssets":{}},"component---src-templates-categories-js":{"chunks":[1,0,7],"assets":["styles.e2d3033dced30e7eb194.css","styles-48fa8a050a65bb8447bd.js","styles-48fa8a050a65bb8447bd.js.map","commons-a6711baf4464e33e2ec1.js","commons-a6711baf4464e33e2ec1.js.map","component---src-templates-categories-js-cfe78ec1e0ea04ee12f0.js","component---src-templates-categories-js-cfe78ec1e0ea04ee12f0.js.map"],"children":{},"childAssets":{}},"component---src-pages-404-js":{"chunks":[1,0,3],"assets":["styles.e2d3033dced30e7eb194.css","styles-48fa8a050a65bb8447bd.js","styles-48fa8a050a65bb8447bd.js.map","commons-a6711baf4464e33e2ec1.js","commons-a6711baf4464e33e2ec1.js.map","component---src-pages-404-js-bf5e10cca5c03eb48f60.js","component---src-pages-404-js-bf5e10cca5c03eb48f60.js.map"],"children":{},"childAssets":{}},"component---src-pages-about-js":{"chunks":[1,0,4],"assets":["styles.e2d3033dced30e7eb194.css","styles-48fa8a050a65bb8447bd.js","styles-48fa8a050a65bb8447bd.js.map","commons-a6711baf4464e33e2ec1.js","commons-a6711baf4464e33e2ec1.js.map","component---src-pages-about-js-ccbb2236993757ee23bc.js","component---src-pages-about-js-ccbb2236993757ee23bc.js.map"],"children":{},"childAssets":{}},"component---src-pages-tags-js":{"chunks":[1,0],"assets":["styles.e2d3033dced30e7eb194.css","styles-48fa8a050a65bb8447bd.js","styles-48fa8a050a65bb8447bd.js.map","commons-a6711baf4464e33e2ec1.js","commons-a6711baf4464e33e2ec1.js.map"],"children":{},"childAssets":{}}},"assetsByChunkName":{"app":["webpack-runtime-87c19cf21ab0e2cb5760.js","framework-b1ec57a693c63eec2e66.js","app-275029329b0bbb5dc6be.js"],"component---src-templates-blog-post-js":["styles.e2d3033dced30e7eb194.css","styles-48fa8a050a65bb8447bd.js","commons-a6711baf4464e33e2ec1.js","component---src-templates-blog-post-js-bba17b4ded4e057a90b4.js"],"component---src-pages-index-js":["styles.e2d3033dced30e7eb194.css","styles-48fa8a050a65bb8447bd.js","commons-a6711baf4464e33e2ec1.js","component---src-pages-index-js-c7540f7aa795a623fa46.js"],"component---src-templates-tags-js":["styles.e2d3033dced30e7eb194.css","styles-48fa8a050a65bb8447bd.js","commons-a6711baf4464e33e2ec1.js","component---src-templates-tags-js-50bd6bd73abdce465f3d.js"],"component---src-templates-categories-js":["styles.e2d3033dced30e7eb194.css","styles-48fa8a050a65bb8447bd.js","commons-a6711baf4464e33e2ec1.js","component---src-templates-categories-js-cfe78ec1e0ea04ee12f0.js"],"component---src-pages-404-js":["styles.e2d3033dced30e7eb194.css","styles-48fa8a050a65bb8447bd.js","commons-a6711baf4464e33e2ec1.js","component---src-pages-404-js-bf5e10cca5c03eb48f60.js"],"component---src-pages-about-js":["styles.e2d3033dced30e7eb194.css","styles-48fa8a050a65bb8447bd.js","commons-a6711baf4464e33e2ec1.js","component---src-pages-about-js-ccbb2236993757ee23bc.js"],"component---src-pages-tags-js":["styles.e2d3033dced30e7eb194.css","styles-48fa8a050a65bb8447bd.js","commons-a6711baf4464e33e2ec1.js"]}}